pytezza/__init__.py
pytezza/build_hh_status_example.py
pytezza/pytezza.py
pytezza-0.1.0.dist-info/DESCRIPTION.rst
pytezza-0.1.0.dist-info/METADATA
pytezza-0.1.0.dist-info/RECORD
pytezza-0.1.0.dist-info/WHEEL
pytezza-0.1.0.dist-info/entry_points.txt
pytezza-0.1.0.dist-info/metadata.json
pytezza-0.1.0.dist-info/top_level.txt
