Metadata-Version: 2.0
Name: pytezza
Version: 0.1.0
Summary: A python/netezza interface utility
Home-page: https://github.com/iamlevis/blurry
Author: Chris Levis
Author-email: chris.levis@eyc.com
License: Apache2
Platform: UNKNOWN
Classifier: Development Status :: 4 - Beta
Classifier: Intended Audience :: System Administrators
Classifier: License :: OSI Approved :: Apache Software License
Classifier: Programming Language :: Python :: 3
Requires-Dist: pandas (>=0.23.0)
